[
  {
    "_schema_version": 3,
    "class_id": 0,
    "class_name": "Cleanser",
    "start_time": 1274.4,
    "end_time": 1274.4,
    "duration": 0.0,
    "best_confidence": 0.692,
    "start_bbox": [
      790.6,
      685.0,
      962.3,
      995.5
    ],
    "end_bbox": [
      790.6,
      685.0,
      962.3,
      995.5
    ],
    "best_bbox": [
      790.6,
      685.0,
      962.3,
      995.5
    ],
    "frame_w": 1080,
    "frame_h": 1920,
    "detection_count": 1,
    "track": [
      {
        "time": 1274.4,
        "bbox": [
          790.6,
          685.0,
          962.3,
          995.5
        ],
        "confidence": 0.692
      }
    ]
  },
  {
    "_schema_version": 3,
    "class_id": 5,
    "class_name": "skin cream",
    "start_time": 1277.6,
    "end_time": 1277.6,
    "duration": 0.0,
    "best_confidence": 0.71,
    "start_bbox": [
      708.2,
      689.5,
      857.8,
      963.7
    ],
    "end_bbox": [
      708.2,
      689.5,
      857.8,
      963.7
    ],
    "best_bbox": [
      708.2,
      689.5,
      857.8,
      963.7
    ],
    "frame_w": 1080,
    "frame_h": 1920,
    "detection_count": 1,
    "track": [
      {
        "time": 1277.6,
        "bbox": [
          708.2,
          689.5,
          857.8,
          963.7
        ],
        "confidence": 0.71
      }
    ]
  },
  {
    "_schema_version": 3,
    "class_id": 5,
    "class_name": "skin cream",
    "start_time": 1284.0,
    "end_time": 1284.0,
    "duration": 0.0,
    "best_confidence": 0.787,
    "start_bbox": [
      714.5,
      706.5,
      858.5,
      999.7
    ],
    "end_bbox": [
      714.5,
      706.5,
      858.5,
      999.7
    ],
    "best_bbox": [
      714.5,
      706.5,
      858.5,
      999.7
    ],
    "frame_w": 1080,
    "frame_h": 1920,
    "detection_count": 1,
    "track": [
      {
        "time": 1284.0,
        "bbox": [
          714.5,
          706.5,
          858.5,
          999.7
        ],
        "confidence": 0.787
      }
    ]
  },
  {
    "_schema_version": 3,
    "class_id": 5,
    "class_name": "skin cream",
    "start_time": 1287.2,
    "end_time": 1288.8,
    "duration": 1.6,
    "best_confidence": 0.836,
    "start_bbox": [
      703.4,
      735.2,
      861.2,
      973.4
    ],
    "end_bbox": [
      699.2,
      726.9,
      879.2,
      983.1
    ],
    "best_bbox": [
      699.2,
      726.9,
      879.2,
      983.1
    ],
    "frame_w": 1080,
    "frame_h": 1920,
    "detection_count": 3,
    "track": [
      {
        "time": 1287.2,
        "bbox": [
          703.4,
          735.2,
          861.2,
          973.4
        ],
        "confidence": 0.807
      },
      {
        "time": 1288.0,
        "bbox": [
          697.2,
          726.2,
          891.0,
          976.8
        ],
        "confidence": 0.831
      },
      {
        "time": 1288.8,
        "bbox": [
          699.2,
          726.9,
          879.2,
          983.1
        ],
        "confidence": 0.836
      }
    ]
  },
  {
    "_schema_version": 3,
    "class_id": 0,
    "class_name": "Cleanser",
    "start_time": 1294.4,
    "end_time": 1294.4,
    "duration": 0.0,
    "best_confidence": 0.554,
    "start_bbox": [
      756.0,
      711.0,
      901.4,
      986.5
    ],
    "end_bbox": [
      756.0,
      711.0,
      901.4,
      986.5
    ],
    "best_bbox": [
      756.0,
      711.0,
      901.4,
      986.5
    ],
    "frame_w": 1080,
    "frame_h": 1920,
    "detection_count": 1,
    "track": [
      {
        "time": 1294.4,
        "bbox": [
          756.0,
          711.0,
          901.4,
          986.5
        ],
        "confidence": 0.554
      }
    ]
  },
  {
    "_schema_version": 3,
    "class_id": 5,
    "class_name": "skin cream",
    "start_time": 1296.0,
    "end_time": 1296.0,
    "duration": 0.0,
    "best_confidence": 0.816,
    "start_bbox": [
      736.6,
      733.8,
      919.4,
      966.5
    ],
    "end_bbox": [
      736.6,
      733.8,
      919.4,
      966.5
    ],
    "best_bbox": [
      736.6,
      733.8,
      919.4,
      966.5
    ],
    "frame_w": 1080,
    "frame_h": 1920,
    "detection_count": 1,
    "track": [
      {
        "time": 1296.0,
        "bbox": [
          736.6,
          733.8,
          919.4,
          966.5
        ],
        "confidence": 0.816
      }
    ]
  },
  {
    "_schema_version": 3,
    "class_id": 5,
    "class_name": "skin cream",
    "start_time": 1300.0,
    "end_time": 1300.0,
    "duration": 0.0,
    "best_confidence": 0.691,
    "start_bbox": [
      686.8,
      747.7,
      833.5,
      1005.2
    ],
    "end_bbox": [
      686.8,
      747.7,
      833.5,
      1005.2
    ],
    "best_bbox": [
      686.8,
      747.7,
      833.5,
      1005.2
    ],
    "frame_w": 1080,
    "frame_h": 1920,
    "detection_count": 1,
    "track": [
      {
        "time": 1300.0,
        "bbox": [
          686.8,
          747.7,
          833.5,
          1005.2
        ],
        "confidence": 0.691
      }
    ]
  },
  {
    "_schema_version": 3,
    "class_id": 5,
    "class_name": "skin cream",
    "start_time": 1301.6,
    "end_time": 1302.4,
    "duration": 0.8,
    "best_confidence": 0.769,
    "start_bbox": [
      755.3,
      708.9,
      957.5,
      996.9
    ],
    "end_bbox": [
      704.1,
      717.2,
      888.2,
      996.9
    ],
    "best_bbox": [
      755.3,
      708.9,
      957.5,
      996.9
    ],
    "frame_w": 1080,
    "frame_h": 1920,
    "detection_count": 2,
    "track": [
      {
        "time": 1301.6,
        "bbox": [
          755.3,
          708.9,
          957.5,
          996.9
        ],
        "confidence": 0.769
      },
      {
        "time": 1302.4,
        "bbox": [
          704.1,
          717.2,
          888.2,
          996.9
        ],
        "confidence": 0.555
      }
    ]
  },
  {
    "_schema_version": 3,
    "class_id": 5,
    "class_name": "skin cream",
    "start_time": 1304.0,
    "end_time": 1305.6,
    "duration": 1.6,
    "best_confidence": 0.815,
    "start_bbox": [
      711.7,
      716.5,
      873.7,
      1021.2
    ],
    "end_bbox": [
      733.8,
      713.1,
      900.0,
      1009.4
    ],
    "best_bbox": [
      711.7,
      716.5,
      873.7,
      1021.2
    ],
    "frame_w": 1080,
    "frame_h": 1920,
    "detection_count": 3,
    "track": [
      {
        "time": 1304.0,
        "bbox": [
          711.7,
          716.5,
          873.7,
          1021.2
        ],
        "confidence": 0.815
      },
      {
        "time": 1304.8,
        "bbox": [
          702.0,
          716.5,
          870.9,
          1019.8
        ],
        "confidence": 0.651
      },
      {
        "time": 1305.6,
        "bbox": [
          733.8,
          713.1,
          900.0,
          1009.4
        ],
        "confidence": 0.796
      }
    ]
  },
  {
    "_schema_version": 3,
    "class_id": 0,
    "class_name": "Cleanser",
    "start_time": 1308.0,
    "end_time": 1308.8,
    "duration": 0.8,
    "best_confidence": 0.624,
    "start_bbox": [
      771.2,
      735.9,
      948.5,
      990.7
    ],
    "end_bbox": [
      767.1,
      726.9,
      955.4,
      995.5
    ],
    "best_bbox": [
      771.2,
      735.9,
      948.5,
      990.7
    ],
    "frame_w": 1080,
    "frame_h": 1920,
    "detection_count": 2,
    "track": [
      {
        "time": 1308.0,
        "bbox": [
          771.2,
          735.9,
          948.5,
          990.7
        ],
        "confidence": 0.624
      },
      {
        "time": 1308.8,
        "bbox": [
          767.1,
          726.9,
          955.4,
          995.5
        ],
        "confidence": 0.557
      }
    ]
  },
  {
    "_schema_version": 3,
    "class_id": 5,
    "class_name": "skin cream",
    "start_time": 1312.0,
    "end_time": 1312.8,
    "duration": 0.8,
    "best_confidence": 0.703,
    "start_bbox": [
      694.4,
      764.3,
      852.2,
      1042.6
    ],
    "end_bbox": [
      669.5,
      745.6,
      805.2,
      1015.6
    ],
    "best_bbox": [
      669.5,
      745.6,
      805.2,
      1015.6
    ],
    "frame_w": 1080,
    "frame_h": 1920,
    "detection_count": 2,
    "track": [
      {
        "time": 1312.0,
        "bbox": [
          694.4,
          764.3,
          852.2,
          1042.6
        ],
        "confidence": 0.566
      },
      {
        "time": 1312.8,
        "bbox": [
          669.5,
          745.6,
          805.2,
          1015.6
        ],
        "confidence": 0.703
      }
    ]
  },
  {
    "_schema_version": 3,
    "class_id": 5,
    "class_name": "skin cream",
    "start_time": 1463.2,
    "end_time": 1463.2,
    "duration": 0.0,
    "best_confidence": 0.66,
    "start_bbox": [
      84.5,
      735.2,
      282.1,
      955.4
    ],
    "end_bbox": [
      84.5,
      735.2,
      282.1,
      955.4
    ],
    "best_bbox": [
      84.5,
      735.2,
      282.1,
      955.4
    ],
    "frame_w": 1080,
    "frame_h": 1920,
    "detection_count": 1,
    "track": [
      {
        "time": 1463.2,
        "bbox": [
          84.5,
          735.2,
          282.1,
          955.4
        ],
        "confidence": 0.66
      }
    ]
  },
  {
    "_schema_version": 3,
    "class_id": 5,
    "class_name": "skin cream",
    "start_time": 1464.8,
    "end_time": 1465.6,
    "duration": 0.8,
    "best_confidence": 0.886,
    "start_bbox": [
      70.7,
      718.6,
      278.3,
      945.7
    ],
    "end_bbox": [
      277.6,
      951.2,
      383.5,
      1152.0
    ],
    "best_bbox": [
      277.6,
      951.2,
      383.5,
      1152.0
    ],
    "frame_w": 1080,
    "frame_h": 1920,
    "detection_count": 2,
    "track": [
      {
        "time": 1464.8,
        "bbox": [
          70.7,
          718.6,
          278.3,
          945.7
        ],
        "confidence": 0.562
      },
      {
        "time": 1465.6,
        "bbox": [
          277.6,
          951.2,
          383.5,
          1152.0
        ],
        "confidence": 0.886
      }
    ]
  },
  {
    "_schema_version": 3,
    "class_id": 5,
    "class_name": "skin cream",
    "start_time": 1480.0,
    "end_time": 1480.0,
    "duration": 0.0,
    "best_confidence": 0.704,
    "start_bbox": [
      202.5,
      670.2,
      358.6,
      927.7
    ],
    "end_bbox": [
      202.5,
      670.2,
      358.6,
      927.7
    ],
    "best_bbox": [
      202.5,
      670.2,
      358.6,
      927.7
    ],
    "frame_w": 1080,
    "frame_h": 1920,
    "detection_count": 1,
    "track": [
      {
        "time": 1480.0,
        "bbox": [
          202.5,
          670.2,
          358.6,
          927.7
        ],
        "confidence": 0.704
      }
    ]
  },
  {
    "_schema_version": 3,
    "class_id": 5,
    "class_name": "skin cream",
    "start_time": 1487.2,
    "end_time": 1487.2,
    "duration": 0.0,
    "best_confidence": 0.552,
    "start_bbox": [
      280.9,
      641.8,
      389.1,
      935.3
    ],
    "end_bbox": [
      280.9,
      641.8,
      389.1,
      935.3
    ],
    "best_bbox": [
      280.9,
      641.8,
      389.1,
      935.3
    ],
    "frame_w": 1080,
    "frame_h": 1920,
    "detection_count": 1,
    "track": [
      {
        "time": 1487.2,
        "bbox": [
          280.9,
          641.8,
          389.1,
          935.3
        ],
        "confidence": 0.552
      }
    ]
  },
  {
    "_schema_version": 3,
    "class_id": 5,
    "class_name": "skin cream",
    "start_time": 1489.6,
    "end_time": 1490.4,
    "duration": 0.8,
    "best_confidence": 0.681,
    "start_bbox": [
      293.0,
      623.4,
      411.9,
      938.8
    ],
    "end_bbox": [
      281.4,
      645.6,
      393.6,
      927.7
    ],
    "best_bbox": [
      293.0,
      623.4,
      411.9,
      938.8
    ],
    "frame_w": 1080,
    "frame_h": 1920,
    "detection_count": 2,
    "track": [
      {
        "time": 1489.6,
        "bbox": [
          293.0,
          623.4,
          411.9,
          938.8
        ],
        "confidence": 0.681
      },
      {
        "time": 1490.4,
        "bbox": [
          281.4,
          645.6,
          393.6,
          927.7
        ],
        "confidence": 0.625
      }
    ]
  },
  {
    "_schema_version": 3,
    "class_id": 0,
    "class_name": "Cleanser",
    "start_time": 1497.6,
    "end_time": 1497.6,
    "duration": 0.0,
    "best_confidence": 0.6,
    "start_bbox": [
      126.7,
      774.0,
      220.2,
      965.1
    ],
    "end_bbox": [
      126.7,
      774.0,
      220.2,
      965.1
    ],
    "best_bbox": [
      126.7,
      774.0,
      220.2,
      965.1
    ],
    "frame_w": 1080,
    "frame_h": 1920,
    "detection_count": 1,
    "track": [
      {
        "time": 1497.6,
        "bbox": [
          126.7,
          774.0,
          220.2,
          965.1
        ],
        "confidence": 0.6
      }
    ]
  },
  {
    "_schema_version": 3,
    "class_id": 5,
    "class_name": "skin cream",
    "start_time": 1834.4,
    "end_time": 1834.4,
    "duration": 0.0,
    "best_confidence": 0.719,
    "start_bbox": [
      720.0,
      757.4,
      814.2,
      942.9
    ],
    "end_bbox": [
      720.0,
      757.4,
      814.2,
      942.9
    ],
    "best_bbox": [
      720.0,
      757.4,
      814.2,
      942.9
    ],
    "frame_w": 1080,
    "frame_h": 1920,
    "detection_count": 1,
    "track": [
      {
        "time": 1834.4,
        "bbox": [
          720.0,
          757.4,
          814.2,
          942.9
        ],
        "confidence": 0.719
      }
    ]
  },
  {
    "_schema_version": 3,
    "class_id": 5,
    "class_name": "skin cream",
    "start_time": 1836.0,
    "end_time": 1836.0,
    "duration": 0.0,
    "best_confidence": 0.589,
    "start_bbox": [
      699.2,
      792.0,
      808.6,
      960.9
    ],
    "end_bbox": [
      699.2,
      792.0,
      808.6,
      960.9
    ],
    "best_bbox": [
      699.2,
      792.0,
      808.6,
      960.9
    ],
    "frame_w": 1080,
    "frame_h": 1920,
    "detection_count": 1,
    "track": [
      {
        "time": 1836.0,
        "bbox": [
          699.2,
          792.0,
          808.6,
          960.9
        ],
        "confidence": 0.589
      }
    ]
  },
  {
    "_schema_version": 3,
    "class_id": 5,
    "class_name": "skin cream",
    "start_time": 1845.6,
    "end_time": 1847.2,
    "duration": 1.6,
    "best_confidence": 0.842,
    "start_bbox": [
      728.3,
      754.6,
      847.4,
      962.3
    ],
    "end_bbox": [
      722.8,
      730.4,
      844.6,
      943.6
    ],
    "best_bbox": [
      722.8,
      730.4,
      844.6,
      943.6
    ],
    "frame_w": 1080,
    "frame_h": 1920,
    "detection_count": 3,
    "track": [
      {
        "time": 1845.6,
        "bbox": [
          728.3,
          754.6,
          847.4,
          962.3
        ],
        "confidence": 0.6
      },
      {
        "time": 1846.4,
        "bbox": [
          704.8,
          754.6,
          810.0,
          951.2
        ],
        "confidence": 0.829
      },
      {
        "time": 1847.2,
        "bbox": [
          722.8,
          730.4,
          844.6,
          943.6
        ],
        "confidence": 0.842
      }
    ]
  },
  {
    "_schema_version": 3,
    "class_id": 0,
    "class_name": "Cleanser",
    "start_time": 1851.2,
    "end_time": 1851.2,
    "duration": 0.0,
    "best_confidence": 0.586,
    "start_bbox": [
      747.0,
      733.2,
      871.6,
      942.2
    ],
    "end_bbox": [
      747.0,
      733.2,
      871.6,
      942.2
    ],
    "best_bbox": [
      747.0,
      733.2,
      871.6,
      942.2
    ],
    "frame_w": 1080,
    "frame_h": 1920,
    "detection_count": 1,
    "track": [
      {
        "time": 1851.2,
        "bbox": [
          747.0,
          733.2,
          871.6,
          942.2
        ],
        "confidence": 0.586
      }
    ]
  },
  {
    "_schema_version": 3,
    "class_id": 4,
    "class_name": "Sheet Mask",
    "start_time": 1855.2,
    "end_time": 1855.2,
    "duration": 0.0,
    "best_confidence": 0.626,
    "start_bbox": [
      833.5,
      884.1,
      902.8,
      958.8
    ],
    "end_bbox": [
      833.5,
      884.1,
      902.8,
      958.8
    ],
    "best_bbox": [
      833.5,
      884.1,
      902.8,
      958.8
    ],
    "frame_w": 1080,
    "frame_h": 1920,
    "detection_count": 1,
    "track": [
      {
        "time": 1855.2,
        "bbox": [
          833.5,
          884.1,
          902.8,
          958.8
        ],
        "confidence": 0.626
      }
    ]
  },
  {
    "_schema_version": 3,
    "class_id": 5,
    "class_name": "skin cream",
    "start_time": 1856.8,
    "end_time": 1856.8,
    "duration": 0.0,
    "best_confidence": 0.582,
    "start_bbox": [
      684.0,
      768.5,
      797.5,
      951.2
    ],
    "end_bbox": [
      684.0,
      768.5,
      797.5,
      951.2
    ],
    "best_bbox": [
      684.0,
      768.5,
      797.5,
      951.2
    ],
    "frame_w": 1080,
    "frame_h": 1920,
    "detection_count": 1,
    "track": [
      {
        "time": 1856.8,
        "bbox": [
          684.0,
          768.5,
          797.5,
          951.2
        ],
        "confidence": 0.582
      }
    ]
  },
  {
    "_schema_version": 3,
    "class_id": 5,
    "class_name": "skin cream",
    "start_time": 1860.0,
    "end_time": 1860.0,
    "duration": 0.0,
    "best_confidence": 0.858,
    "start_bbox": [
      739.4,
      726.9,
      857.1,
      954.0
    ],
    "end_bbox": [
      739.4,
      726.9,
      857.1,
      954.0
    ],
    "best_bbox": [
      739.4,
      726.9,
      857.1,
      954.0
    ],
    "frame_w": 1080,
    "frame_h": 1920,
    "detection_count": 1,
    "track": [
      {
        "time": 1860.0,
        "bbox": [
          739.4,
          726.9,
          857.1,
          954.0
        ],
        "confidence": 0.858
      }
    ]
  },
  {
    "_schema_version": 3,
    "class_id": 5,
    "class_name": "skin cream",
    "start_time": 1866.4,
    "end_time": 1866.4,
    "duration": 0.0,
    "best_confidence": 0.916,
    "start_bbox": [
      872.3,
      764.3,
      1046.8,
      991.4
    ],
    "end_bbox": [
      872.3,
      764.3,
      1046.8,
      991.4
    ],
    "best_bbox": [
      872.3,
      764.3,
      1046.8,
      991.4
    ],
    "frame_w": 1080,
    "frame_h": 1920,
    "detection_count": 1,
    "track": [
      {
        "time": 1866.4,
        "bbox": [
          872.3,
          764.3,
          1046.8,
          991.4
        ],
        "confidence": 0.916
      }
    ]
  },
  {
    "_schema_version": 3,
    "class_id": 5,
    "class_name": "skin cream",
    "start_time": 1869.6,
    "end_time": 1869.6,
    "duration": 0.0,
    "best_confidence": 0.717,
    "start_bbox": [
      799.6,
      735.2,
      933.9,
      948.5
    ],
    "end_bbox": [
      799.6,
      735.2,
      933.9,
      948.5
    ],
    "best_bbox": [
      799.6,
      735.2,
      933.9,
      948.5
    ],
    "frame_w": 1080,
    "frame_h": 1920,
    "detection_count": 1,
    "track": [
      {
        "time": 1869.6,
        "bbox": [
          799.6,
          735.2,
          933.9,
          948.5
        ],
        "confidence": 0.717
      }
    ]
  },
  {
    "_schema_version": 3,
    "class_id": 1,
    "class_name": "Serum",
    "start_time": 3236.0,
    "end_time": 3236.0,
    "duration": 0.0,
    "best_confidence": 0.607,
    "start_bbox": [
      999.7,
      866.1,
      1071.7,
      972.7
    ],
    "end_bbox": [
      999.7,
      866.1,
      1071.7,
      972.7
    ],
    "best_bbox": [
      999.7,
      866.1,
      1071.7,
      972.7
    ],
    "frame_w": 1080,
    "frame_h": 1920,
    "detection_count": 1,
    "track": [
      {
        "time": 3236.0,
        "bbox": [
          999.7,
          866.1,
          1071.7,
          972.7
        ],
        "confidence": 0.607
      }
    ]
  },
  {
    "_schema_version": 3,
    "class_id": 0,
    "class_name": "Cleanser",
    "start_time": 4218.4,
    "end_time": 4218.4,
    "duration": 0.0,
    "best_confidence": 0.594,
    "start_bbox": [
      756.0,
      801.7,
      974.8,
      1034.3
    ],
    "end_bbox": [
      756.0,
      801.7,
      974.8,
      1034.3
    ],
    "best_bbox": [
      756.0,
      801.7,
      974.8,
      1034.3
    ],
    "frame_w": 1080,
    "frame_h": 1920,
    "detection_count": 1,
    "track": [
      {
        "time": 4218.4,
        "bbox": [
          756.0,
          801.7,
          974.8,
          1034.3
        ],
        "confidence": 0.594
      }
    ]
  },
  {
    "_schema_version": 3,
    "class_id": 0,
    "class_name": "Cleanser",
    "start_time": 4228.8,
    "end_time": 4228.8,
    "duration": 0.0,
    "best_confidence": 0.658,
    "start_bbox": [
      739.4,
      714.5,
      972.0,
      1041.2
    ],
    "end_bbox": [
      739.4,
      714.5,
      972.0,
      1041.2
    ],
    "best_bbox": [
      739.4,
      714.5,
      972.0,
      1041.2
    ],
    "frame_w": 1080,
    "frame_h": 1920,
    "detection_count": 1,
    "track": [
      {
        "time": 4228.8,
        "bbox": [
          739.4,
          714.5,
          972.0,
          1041.2
        ],
        "confidence": 0.658
      }
    ]
  },
  {
    "_schema_version": 3,
    "class_id": 0,
    "class_name": "Cleanser",
    "start_time": 7330.4,
    "end_time": 7330.4,
    "duration": 0.0,
    "best_confidence": 0.649,
    "start_bbox": [
      760.2,
      743.5,
      868.2,
      951.2
    ],
    "end_bbox": [
      760.2,
      743.5,
      868.2,
      951.2
    ],
    "best_bbox": [
      760.2,
      743.5,
      868.2,
      951.2
    ],
    "frame_w": 1080,
    "frame_h": 1920,
    "detection_count": 1,
    "track": [
      {
        "time": 7330.4,
        "bbox": [
          760.2,
          743.5,
          868.2,
          951.2
        ],
        "confidence": 0.649
      }
    ]
  },
  {
    "_schema_version": 3,
    "class_id": 5,
    "class_name": "skin cream",
    "start_time": 7338.4,
    "end_time": 7338.4,
    "duration": 0.0,
    "best_confidence": 0.562,
    "start_bbox": [
      762.9,
      656.3,
      865.4,
      944.3
    ],
    "end_bbox": [
      762.9,
      656.3,
      865.4,
      944.3
    ],
    "best_bbox": [
      762.9,
      656.3,
      865.4,
      944.3
    ],
    "frame_w": 1080,
    "frame_h": 1920,
    "detection_count": 1,
    "track": [
      {
        "time": 7338.4,
        "bbox": [
          762.9,
          656.3,
          865.4,
          944.3
        ],
        "confidence": 0.562
      }
    ]
  },
  {
    "_schema_version": 3,
    "class_id": 5,
    "class_name": "skin cream",
    "start_time": 7341.6,
    "end_time": 7341.6,
    "duration": 0.0,
    "best_confidence": 0.556,
    "start_bbox": [
      758.8,
      665.7,
      861.2,
      948.5
    ],
    "end_bbox": [
      758.8,
      665.7,
      861.2,
      948.5
    ],
    "best_bbox": [
      758.8,
      665.7,
      861.2,
      948.5
    ],
    "frame_w": 1080,
    "frame_h": 1920,
    "detection_count": 1,
    "track": [
      {
        "time": 7341.6,
        "bbox": [
          758.8,
          665.7,
          861.2,
          948.5
        ],
        "confidence": 0.556
      }
    ]
  },
  {
    "_schema_version": 3,
    "class_id": 5,
    "class_name": "skin cream",
    "start_time": 7343.2,
    "end_time": 7344.0,
    "duration": 0.8,
    "best_confidence": 0.583,
    "start_bbox": [
      759.5,
      657.7,
      866.1,
      942.9
    ],
    "end_bbox": [
      757.4,
      661.2,
      868.2,
      946.4
    ],
    "best_bbox": [
      759.5,
      657.7,
      866.1,
      942.9
    ],
    "frame_w": 1080,
    "frame_h": 1920,
    "detection_count": 2,
    "track": [
      {
        "time": 7343.2,
        "bbox": [
          759.5,
          657.7,
          866.1,
          942.9
        ],
        "confidence": 0.583
      },
      {
        "time": 7344.0,
        "bbox": [
          757.4,
          661.2,
          868.2,
          946.4
        ],
        "confidence": 0.564
      }
    ]
  },
  {
    "_schema_version": 3,
    "class_id": 5,
    "class_name": "skin cream",
    "start_time": 7345.6,
    "end_time": 7345.6,
    "duration": 0.0,
    "best_confidence": 0.566,
    "start_bbox": [
      762.9,
      659.1,
      865.4,
      945.7
    ],
    "end_bbox": [
      762.9,
      659.1,
      865.4,
      945.7
    ],
    "best_bbox": [
      762.9,
      659.1,
      865.4,
      945.7
    ],
    "frame_w": 1080,
    "frame_h": 1920,
    "detection_count": 1,
    "track": [
      {
        "time": 7345.6,
        "bbox": [
          762.9,
          659.1,
          865.4,
          945.7
        ],
        "confidence": 0.566
      }
    ]
  },
  {
    "_schema_version": 3,
    "class_id": 5,
    "class_name": "skin cream",
    "start_time": 7348.8,
    "end_time": 7348.8,
    "duration": 0.0,
    "best_confidence": 0.551,
    "start_bbox": [
      761.5,
      662.9,
      866.8,
      945.7
    ],
    "end_bbox": [
      761.5,
      662.9,
      866.8,
      945.7
    ],
    "best_bbox": [
      761.5,
      662.9,
      866.8,
      945.7
    ],
    "frame_w": 1080,
    "frame_h": 1920,
    "detection_count": 1,
    "track": [
      {
        "time": 7348.8,
        "bbox": [
          761.5,
          662.9,
          866.8,
          945.7
        ],
        "confidence": 0.551
      }
    ]
  },
  {
    "_schema_version": 3,
    "class_id": 5,
    "class_name": "skin cream",
    "start_time": 7351.2,
    "end_time": 7351.2,
    "duration": 0.0,
    "best_confidence": 0.572,
    "start_bbox": [
      765.0,
      654.6,
      873.0,
      945.7
    ],
    "end_bbox": [
      765.0,
      654.6,
      873.0,
      945.7
    ],
    "best_bbox": [
      765.0,
      654.6,
      873.0,
      945.7
    ],
    "frame_w": 1080,
    "frame_h": 1920,
    "detection_count": 1,
    "track": [
      {
        "time": 7351.2,
        "bbox": [
          765.0,
          654.6,
          873.0,
          945.7
        ],
        "confidence": 0.572
      }
    ]
  },
  {
    "_schema_version": 3,
    "class_id": 5,
    "class_name": "skin cream",
    "start_time": 7356.0,
    "end_time": 7356.0,
    "duration": 0.0,
    "best_confidence": 0.585,
    "start_bbox": [
      752.5,
      683.0,
      856.4,
      951.2
    ],
    "end_bbox": [
      752.5,
      683.0,
      856.4,
      951.2
    ],
    "best_bbox": [
      752.5,
      683.0,
      856.4,
      951.2
    ],
    "frame_w": 1080,
    "frame_h": 1920,
    "detection_count": 1,
    "track": [
      {
        "time": 7356.0,
        "bbox": [
          752.5,
          683.0,
          856.4,
          951.2
        ],
        "confidence": 0.585
      }
    ]
  },
  {
    "_schema_version": 3,
    "class_id": 5,
    "class_name": "skin cream",
    "start_time": 7359.2,
    "end_time": 7359.2,
    "duration": 0.0,
    "best_confidence": 0.604,
    "start_bbox": [
      753.2,
      677.1,
      857.1,
      954.0
    ],
    "end_bbox": [
      753.2,
      677.1,
      857.1,
      954.0
    ],
    "best_bbox": [
      753.2,
      677.1,
      857.1,
      954.0
    ],
    "frame_w": 1080,
    "frame_h": 1920,
    "detection_count": 1,
    "track": [
      {
        "time": 7359.2,
        "bbox": [
          753.2,
          677.1,
          857.1,
          954.0
        ],
        "confidence": 0.604
      }
    ]
  },
  {
    "_schema_version": 3,
    "class_id": 4,
    "class_name": "Sheet Mask",
    "start_time": 7641.6,
    "end_time": 7642.4,
    "duration": 0.8,
    "best_confidence": 0.731,
    "start_bbox": [
      749.8,
      837.0,
      867.5,
      929.8
    ],
    "end_bbox": [
      732.5,
      834.9,
      854.3,
      930.5
    ],
    "best_bbox": [
      749.8,
      837.0,
      867.5,
      929.8
    ],
    "frame_w": 1080,
    "frame_h": 1920,
    "detection_count": 2,
    "track": [
      {
        "time": 7641.6,
        "bbox": [
          749.8,
          837.0,
          867.5,
          929.8
        ],
        "confidence": 0.731
      },
      {
        "time": 7642.4,
        "bbox": [
          732.5,
          834.9,
          854.3,
          930.5
        ],
        "confidence": 0.715
      }
    ]
  },
  {
    "_schema_version": 3,
    "class_id": 4,
    "class_name": "Sheet Mask",
    "start_time": 7645.6,
    "end_time": 7645.6,
    "duration": 0.0,
    "best_confidence": 0.566,
    "start_bbox": [
      746.3,
      783.7,
      850.2,
      886.2
    ],
    "end_bbox": [
      746.3,
      783.7,
      850.2,
      886.2
    ],
    "best_bbox": [
      746.3,
      783.7,
      850.2,
      886.2
    ],
    "frame_w": 1080,
    "frame_h": 1920,
    "detection_count": 1,
    "track": [
      {
        "time": 7645.6,
        "bbox": [
          746.3,
          783.7,
          850.2,
          886.2
        ],
        "confidence": 0.566
      }
    ]
  },
  {
    "_schema_version": 3,
    "class_id": 0,
    "class_name": "Cleanser",
    "start_time": 7657.6,
    "end_time": 7657.6,
    "duration": 0.0,
    "best_confidence": 0.579,
    "start_bbox": [
      688.2,
      702.3,
      870.9,
      967.8
    ],
    "end_bbox": [
      688.2,
      702.3,
      870.9,
      967.8
    ],
    "best_bbox": [
      688.2,
      702.3,
      870.9,
      967.8
    ],
    "frame_w": 1080,
    "frame_h": 1920,
    "detection_count": 1,
    "track": [
      {
        "time": 7657.6,
        "bbox": [
          688.2,
          702.3,
          870.9,
          967.8
        ],
        "confidence": 0.579
      }
    ]
  },
  {
    "_schema_version": 3,
    "class_id": 0,
    "class_name": "Cleanser",
    "start_time": 7664.8,
    "end_time": 7664.8,
    "duration": 0.0,
    "best_confidence": 0.584,
    "start_bbox": [
      717.9,
      699.6,
      904.8,
      954.0
    ],
    "end_bbox": [
      717.9,
      699.6,
      904.8,
      954.0
    ],
    "best_bbox": [
      717.9,
      699.6,
      904.8,
      954.0
    ],
    "frame_w": 1080,
    "frame_h": 1920,
    "detection_count": 1,
    "track": [
      {
        "time": 7664.8,
        "bbox": [
          717.9,
          699.6,
          904.8,
          954.0
        ],
        "confidence": 0.584
      }
    ]
  },
  {
    "_schema_version": 3,
    "class_id": 0,
    "class_name": "Cleanser",
    "start_time": 7676.0,
    "end_time": 7676.0,
    "duration": 0.0,
    "best_confidence": 0.551,
    "start_bbox": [
      731.1,
      702.7,
      913.8,
      946.4
    ],
    "end_bbox": [
      731.1,
      702.7,
      913.8,
      946.4
    ],
    "best_bbox": [
      731.1,
      702.7,
      913.8,
      946.4
    ],
    "frame_w": 1080,
    "frame_h": 1920,
    "detection_count": 1,
    "track": [
      {
        "time": 7676.0,
        "bbox": [
          731.1,
          702.7,
          913.8,
          946.4
        ],
        "confidence": 0.551
      }
    ]
  }
]